{
  "type": "draw",
  "resultFn": "__grid",
  "demoArgs": [],
  "title": "Your add4, doubling every number",
  "setup": "# --- grid helper (hidden) — the 4-bit adder doubling each number ---\n# Laid out wide (the canvas has more room sideways): each COLUMN shows n + n\n# computed by the student's own add4, in 5-bit binary (the sum can reach 30, so\n# there's a 16s place). Read down a column for its bits. Until add4 works the\n# bit cells show '?'; the number row and place-value labels always render.\ndef __grid():\n    add = globals().get(\"add4\")\n    nums = list(range(16))\n\n    def sum_of(n):\n        if add is None:\n            return None\n        try:\n            v = add(n, n)\n            return v if isinstance(v, int) else None\n        except Exception:\n            return None\n\n    sums = [sum_of(n) for n in nums]\n    rows = [[\"n\"] + [str(n) for n in nums]]\n    for p_idx, place in enumerate([16, 8, 4, 2, 1]):\n        shift = 4 - p_idx\n        row = [str(place)]\n        for n in nums:\n            s = sums[n]\n            if s is None:\n                row.append(\"?\")\n            elif (s >> shift) & 1:\n                row.append(\"green\")\n            else:\n                row.append(\"\")\n        rows.append(row)\n    return {\n        \"grid\": rows,\n        \"caption\": \"Each column shows n + n (double it!) from your add4, in binary - read down: 16s, 8s, 4s, 2s, 1s. The lit pattern climbs as the sum grows, and the 1s row is always empty because doubling is always even. A ? means add4 isn't finished yet.\",\n    }\n"
}
